docimage/__init__.py
docimage/fuzzyimgsearch.py
docimage/preprocessing.py
docimage-0.0.2.dist-info/DESCRIPTION.rst
docimage-0.0.2.dist-info/METADATA
docimage-0.0.2.dist-info/RECORD
docimage-0.0.2.dist-info/WHEEL
docimage-0.0.2.dist-info/metadata.json
docimage-0.0.2.dist-info/top_level.txt
