Metadata-Version: 2.0
Name: docimage
Version: 0.0.2
Summary: .
Home-page: https://github.com/vedavaapi/docimage
Author: Sanskrit programmers
Author-email: sanskrit-programmers@googlegroups.com
License: MIT
Keywords: sanskrit schema samskrtam samskritam
Platform: UNKNOWN
Classifier: Development Status :: 3 - Alpha
Classifier: Intended Audience :: Education
Classifier: Intended Audience :: Science/Research
Classifier: Intended Audience :: Developers
Classifier: License :: OSI Approved :: MIT License
Classifier: Programming Language :: Python :: 2
Classifier: Programming Language :: Python :: 2.7
Classifier: Programming Language :: Python :: 3
Classifier: Programming Language :: Python :: 3.3
Classifier: Programming Language :: Python :: 3.4
Classifier: Programming Language :: Python :: 3.5
Requires-Dist: Pillow
Requires-Dist: numpy
Requires-Dist: opencv-python
Requires-Dist: sanskrit-data
Requires-Dist: scikit-image
Requires-Dist: scipy
Provides-Extra: test
Requires-Dist: matplotlib; extra == 'test'
